odoo/addons/shopinvader/README.rst
odoo/addons/shopinvader/__init__.py
odoo/addons/shopinvader/__manifest__.py
odoo/addons/shopinvader/exceptions.py
odoo/addons/shopinvader/shopinvader_response.py
odoo/addons/shopinvader/utils.py
odoo/addons/shopinvader/components/__init__.py
odoo/addons/shopinvader/components/access_info.py
odoo/addons/shopinvader/components/core.py
odoo/addons/shopinvader/components/partner_validator.py
odoo/addons/shopinvader/components/product_product_event_listener.py
odoo/addons/shopinvader/components/res_partner_event_listener.py
odoo/addons/shopinvader/components/shopinvader_partner_event_listener.py
odoo/addons/shopinvader/controllers/__init__.py
odoo/addons/shopinvader/controllers/main.py
odoo/addons/shopinvader/data/cart_step.xml
odoo/addons/shopinvader/data/ir_export_category.xml
odoo/addons/shopinvader/data/ir_export_product.xml
odoo/addons/shopinvader/data/mail_activity_data.xml
odoo/addons/shopinvader/data/queue_job_channel_data.xml
odoo/addons/shopinvader/data/queue_job_function_data.xml
odoo/addons/shopinvader/data/res_partner.xml
odoo/addons/shopinvader/demo/account_demo.xml
odoo/addons/shopinvader/demo/auth_api_key_demo.xml
odoo/addons/shopinvader/demo/backend_demo.xml
odoo/addons/shopinvader/demo/email_demo.xml
odoo/addons/shopinvader/demo/notification_demo.xml
odoo/addons/shopinvader/demo/partner_demo.xml
odoo/addons/shopinvader/demo/pricelist_demo.xml
odoo/addons/shopinvader/demo/product_attribute_value_demo.xml
odoo/addons/shopinvader/demo/product_category_demo.xml
odoo/addons/shopinvader/demo/product_filter_demo.xml
odoo/addons/shopinvader/demo/product_product_demo.xml
odoo/addons/shopinvader/demo/sale_demo.xml
odoo/addons/shopinvader/i18n/shopinvader.pot
odoo/addons/shopinvader/migrations/13.0.1.7.0/post-migrate.py
odoo/addons/shopinvader/migrations/13.0.6.3.0/pre-migration.py
odoo/addons/shopinvader/models/__init__.py
odoo/addons/shopinvader/models/account_move.py
odoo/addons/shopinvader/models/product_category.py
odoo13_addon_shopinvader-13.0.6.10.0.dist-info/METADATA
odoo13_addon_shopinvader-13.0.6.10.0.dist-info/WHEEL
odoo13_addon_shopinvader-13.0.6.10.0.dist-info/top_level.txt
odoo13_addon_shopinvader-13.0.6.10.0.dist-info/RECORD
