Metadata-Version: 2.1
Name: odoo13-addon-shopinvader
Version: 13.0.6.10.0
Summary: Shopinvader
Home-page: https://github.com/shopinvader/odoo-shopinvader
Author: Akretion
License: AGPL-3
Platform: UNKNOWN
Classifier: Programming Language :: Python
Classifier: Framework :: Odoo
Classifier: Framework :: Odoo :: 13.0
Classifier: License :: OSI Approved :: GNU Affero General Public License v3
Requires-Python: >=3.5
Requires-Dist: cerberus
Requires-Dist: odoo13-addon-auth-api-key
Requires-Dist: odoo13-addon-base-jsonify
Requires-Dist: odoo13-addon-base-rest
Requires-Dist: odoo13-addon-base-sparse-field-list-support
Requires-Dist: odoo13-addon-base-url
Requires-Dist: odoo13-addon-component-event
Requires-Dist: odoo13-addon-onchange-helper
Requires-Dist: odoo13-addon-queue-job
Requires-Dist: odoo13-addon-sale-discount-display-amount
Requires-Dist: odoo (<13.1dev,>=13.0a)
Requires-Dist: unidecode
